{
    "quizzes": [
        {
            "title": "Minnesota Driver's Manual Quiz (Pages 30-40)",
            "questions": [
                {
                    "number": 1,
                    "question": "What is the minimum age to apply for a Class D driver's license in Minnesota?",
                    "options": ["15", "16", "17", "18"]
                },
                {
                    "number": 2,
                    "question": "What must you do if you change your name or address before your license expires?",
                    "options": ["Nothing", "Apply for a duplicate license within 30 days", "Wait until your license expires", "Notify the police"]
                },
                {
                    "number": 3,
                    "question": "How long is a Minnesota driver's license valid after issuance?",
                    "options": ["2 years", "4 years", "6 years", "10 years"]
                },
                {
                    "number": 4,
                    "question": "What is required for a driver’s license renewal?",
                    "options": ["A vision test", "A written test", "A road test", "No requirements"]
                },
                {
                    "number": 5,
                    "question": "If you lose your driver's license, what must you present to apply for a duplicate?",
                    "options": ["A birth certificate", "Proper identification", "A social security card", "A utility bill"]
                },
                {
                    "number": 6,
                    "question": "What is the fee for renewing a driver's license in Minnesota?",
                    "options": ["$5", "$10", "It varies by age and type of license", "$20"]
                },
                {
                    "number": 7,
                    "question": "What is the consequence of failing to renew your driver's license before it expires?",
                    "options": ["You can still drive", "You must retake the written test", "You may face fines or penalties", "No consequence"]
                },
                {
                    "number": 8,
                    "question": "What is the purpose of the Minnesota Department of Transportation Office of Freight and Commercial Vehicle Operations?",
                    "options": ["To issue regular driver's licenses", "To oversee commercial vehicle operations", "To conduct road tests", "To provide driver education"]
                },
                {
                    "number": 9,
                    "question": "What is required for a commercial driver's license (CDL) in Minnesota?",
                    "options": ["A high school diploma", "A medical examiner’s certificate", "A written test only", "No requirements"]
                },
                {
                    "number": 10,
                    "question": "What is the maximum weight for vehicles that may require a CDL?",
                    "options": ["5,000 pounds", "10,000 pounds", "26,000 pounds", "40,000 pounds"]
                },
                {
                    "number": 11,
                    "question": "What is the minimum age to obtain a CDL in Minnesota?",
                    "options": ["16", "18", "21", "25"]
                },
                {
                    "number": 12,
                    "question": "What must a driver do if they are in active military service and their license is about to expire?",
                    "options": ["Ignore it", "Renew it before leaving", "Notify the DMV", "It remains valid while in service"]
                },
                {
                    "number": 13,
                    "question": "What is the requirement for a person under 21 to obtain a CDL?",
                    "options": ["Must have a parent’s permission", "Must pass a written test", "Must have a specific restriction on the license", "All of the above"]
                },
                {
                    "number": 14,
                    "question": "What is the consequence of operating a commercial vehicle without a valid CDL?",
                    "options": ["A warning", "A fine", "Possible jail time", "All of the above"]
                },
                {
                    "number": 15,
                    "question": "What is the purpose of the Minnesota Commercial Driver’s Manual?",
                    "options": ["To provide information on regular driver’s licenses", "To outline requirements for commercial drivers", "To teach defensive driving techniques", "To provide information on vehicle maintenance"]
                },
                {
                    "number": 16,
                    "question": "What must you do if you change your name after obtaining your driver's license?",
                    "options": ["Nothing", "Apply for a duplicate license", "Wait until your license expires", "Notify your insurance company"]
                },
                {
                    "number": 17,
                    "question": "What is the requirement for a restricted farm work driver’s license?",
                    "options": ["Must be at least 14 years old", "Must complete a driver education course", "Must be employed on a farm", "All of the above"]
                },
                {
                    "number": 18,
                    "question": "What is the maximum distance a restricted farm work driver can drive from their farmhouse?",
                    "options": ["20 miles", "30 miles", "40 miles", "50 miles"]
                },
                {
                    "number": 19,
                    "question": "What is the consequence of providing false information on your driver's license application?",
                    "options": ["A warning", "A fine", "Loss of driving privileges", "No consequence"]
                },
                {
                    "number": 20,
                    "question": "What is the requirement for obtaining a motorized bicycle (moped) permit?",
                    "options": ["Must be at least 15 years old", "Must complete a written test", "Must have a parent’s permission", "All of the above"]
                }
            ]
        }
    ]
}